pydegensac/__init__.py
pydegensac/libgcc_s_seh-1.dll
pydegensac/libgfortran-5.dll
pydegensac/liblapack.dll
pydegensac/libquadmath-0.dll
pydegensac/libwinpthread-1.dll
pydegensac/openblas.dll
pydegensac/pydegensac.cp38-win_amd64.pyd
pydegensac/utils.py
pydegensac-0.2.1.dist-info/LICENSE
pydegensac-0.2.1.dist-info/METADATA
pydegensac-0.2.1.dist-info/WHEEL
pydegensac-0.2.1.dist-info/top_level.txt
pydegensac-0.2.1.dist-info/RECORD
