Metadata-Version: 2.1
Name: pydegensac
Version: 0.2.1
Summary: Advanced RANSAC (DEGENSAC) with bells and whistles for H and F estimation
Home-page: https://github.com/ducha-aiki/pydegensac
Download-URL: https://github.com/ducha-aiki/pydegensac/archive/v_0.12.tar.gz
Author: Ondra Chum, Dmytro Mishkin
Author-email: ducha.aiki@gmail.com
License: MIT
License-File: LICENSE
Requires-Dist: numpy
